activegraf_python/__init__.py
activegraf_python/requirements.txt
activegraf_python/authentication_manager/AuthenticationManager.py
activegraf_python/communication/AuthorizationRequestMessage.py
activegraf_python/communication/AxisChanged.py
activegraf_python/communication/AxisDataChange.py
activegraf_python/communication/CellValueChanged.py
activegraf_python/communication/ComponentCommunicator.py
activegraf_python/communication/GrafDataChange.py
activegraf_python/communication/GrafDataChangedEvent.py
activegraf_python/communication/GrafDataRowStreamedData.py
activegraf_python/communication/GrafDataService.py
activegraf_python/communication/HandleGrafDataChangesRequest.py
activegraf_python/communication/InitializeGrafDataContentStreamedMessage.py
activegraf_python/communication/Message.py
activegraf_python/communication/MessageHeader.py
activegraf_python/communication/StreamChannel.py
activegraf_python/communication/ToggleGlobalLoadingRequest.py
activegraf_python/exceptions/AuthorizationFailedException.py
activegraf_python/models/ActiveGrafData.py
activegraf_python/models/AuthorizationResult.py
activegraf_python/models/CellData.py
activegraf_python/models/CellType.py
activegraf_python/models/GrafData.py
activegraf_python/models/GrafDataDefinition.py
activegraf_python/models/GrafDataMutator.py
activegraf_python/models/HandshakeResult.py
activegraf_python/models/Place.py
activegraf_python/utils/CellDataUtils.py
activegraf_python-1.1.2.dist-info/METADATA
activegraf_python-1.1.2.dist-info/WHEEL
activegraf_python-1.1.2.dist-info/licenses/LICENSE
activegraf_python-1.1.2.dist-info/RECORD
