Metadata-Version: 2.4
Name: activegraf_python
Version: 1.1.2
Summary: ActiveGraf ultimate what-if analysis tool API package
Project-URL: homepage, https://activegraf.com
Author-email: Zsolt Nagy <zsolt.nagy@activegraf.com>
Maintainer-email: Zsolt Nagy <zsolt.nagy@activegraf.com>
License: Proprietary (https://activegraf.com/eula)
License-File: LICENSE
Classifier: Operating System :: OS Independent
Classifier: Programming Language :: Python :: 3
Requires-Python: >=3.10
Requires-Dist: events
Requires-Dist: jsonpickle
Requires-Dist: signalrcore
